tfvars2json/__init__.py
tfvars2json/__main__.py
tfvars2json/tfvars2json.py
tfvars2json-0.0.1.dist-info/entry_points.txt
tfvars2json-0.0.1.dist-info/WHEEL
tfvars2json-0.0.1.dist-info/METADATA
tfvars2json-0.0.1.dist-info/RECORD
